pyrqlite/__init__.py
pyrqlite/_ephemeral.py
pyrqlite/connections.py
pyrqlite/constants.py
pyrqlite/cursors.py
pyrqlite/dbapi2.py
pyrqlite/exceptions.py
pyrqlite/extensions.py
pyrqlite/row.py
pyrqlite/types.py
pyrqlite-2.2.3.dist-info/LICENSE
pyrqlite-2.2.3.dist-info/METADATA
pyrqlite-2.2.3.dist-info/WHEEL
pyrqlite-2.2.3.dist-info/top_level.txt
pyrqlite-2.2.3.dist-info/RECORD
